bitscrunch_sdk/__init__.py
bitscrunch_sdk/sdk.py
bitscrunch_sdk-1.0.1.dist-info/METADATA
bitscrunch_sdk-1.0.1.dist-info/WHEEL
bitscrunch_sdk-1.0.1.dist-info/top_level.txt
bitscrunch_sdk-1.0.1.dist-info/RECORD
