Metadata-Version: 2.1
Name: bitscrunch-sdk
Version: 1.0.1
Summary: Python SDK for interacting with the BitsCrunch API
Home-page: https://docs.bitscrunch.com
Author: Ashok Varadharajan
Author-email: ashok@bitscrunch.com
License: Apache License 2.0
Project-URL: Documentation, https://github.com/bitscrunch-protocol/bitscrunch-sdk
Project-URL: Bug Tracker, https://github.com/bitscrunch-protocol/bitscrunch-sdk/issues
Project-URL: Source Code, https://github.com/bitscrunch-protocol/bitscrunch-sdk
Classifier: Development Status :: 4 - Beta
Classifier: Programming Language :: Python :: 3
Classifier: Programming Language :: Python :: 3.8
Classifier: Programming Language :: Python :: 3.9
Classifier: Programming Language :: Python :: 3.10
Classifier: License :: OSI Approved :: Apache Software License
Classifier: Operating System :: OS Independent
Requires-Python: >=3.8
Requires-Dist: httpx>=0.24.1
Requires-Dist: pycryptodome>=3.17
Provides-Extra: dev
Requires-Dist: pytest>=7.0; extra == "dev"
Requires-Dist: black>=23.0; extra == "dev"
Requires-Dist: flake8>=6.0; extra == "dev"
Requires-Dist: mypy>=0.991; extra == "dev"
